{"assets/hi.gif":["assets/hi.gif"],"assets/logo.png":["assets/logo.png"],"assets/photos/black-white.png":["assets/photos/black-white.png"],"assets/photos/colored.jpg":["assets/photos/colored.jpg"],"assets/photos/mobile.png":["assets/photos/mobile.png"],"assets/projects/android.png":["assets/projects/android.png"],"assets/projects/attendance-system.png":["assets/projects/attendance-system.png"],"assets/projects/bleep-logo.jpg":["assets/projects/bleep-logo.jpg"],"assets/projects/bleep-poster.jpg":["assets/projects/bleep-poster.jpg"],"assets/projects/bookbas-icon.png":["assets/projects/bookbas-icon.png"],"assets/projects/bookbas-poster.jpg":["assets/projects/bookbas-poster.jpg"],"assets/projects/bounty-poster.jpg":["assets/projects/bounty-poster.jpg"],"assets/projects/captcha.png":["assets/projects/captcha.png"],"assets/projects/flutter.png":["assets/projects/flutter.png"],"assets/projects/python.png":["assets/projects/python.png"],"assets/projects/wanted-luffy.png":["assets/projects/wanted-luffy.png"],"assets/services/app.png":["assets/services/app.png"],"assets/services/automation.png":["assets/services/automation.png"],"assets/services/backend.png":["assets/services/backend.png"],"assets/services/blog.png":["assets/services/blog.png"],"assets/services/coding.png":["assets/services/coding.png"],"assets/services/data-science.png":["assets/services/data-science.png"],"assets/services/fiverr.png":["assets/services/fiverr.png"],"assets/services/mobile-development.png":["assets/services/mobile-development.png"],"assets/services/open.png":["assets/services/open.png"],"assets/services/open_b.png":["assets/services/open_b.png"],"assets/services/rapid.png":["assets/services/rapid.png"],"assets/services/ui.png":["assets/services/ui.png"],"assets/work/7span-logo.png":["assets/work/7span-logo.png"],"assets/work/bookbas.webp":["assets/work/bookbas.webp"],"assets/work/techgroot-logo.jpg":["assets/work/techgroot-logo.jpg"],"assets/work/trent-logo.png":["assets/work/trent-logo.png"],"data.json":["data.json"],"fonts/agustina/agustina.otf":["fonts/agustina/agustina.otf"],"fonts/montserrat/montserrat.ttf":["fonts/montserrat/montserrat.ttf"],"fonts/poppins/Poppins-Bold.ttf":["fonts/poppins/Poppins-Bold.ttf"],"fonts/poppins/Poppins-Italic.ttf":["fonts/poppins/Poppins-Italic.ttf"],"fonts/poppins/Poppins-Light.ttf":["fonts/poppins/Poppins-Light.ttf"],"fonts/poppins/Poppins-Medium.ttf":["fonts/poppins/Poppins-Medium.ttf"],"fonts/poppins/Poppins-Regular.ttf":["fonts/poppins/Poppins-Regular.ttf"],"fonts/poppins/Poppins-SemiBold.ttf":["fonts/poppins/Poppins-SemiBold.ttf"],"packages/cupertino_icons/assets/CupertinoIcons.ttf":["packages/cupertino_icons/assets/CupertinoIcons.ttf"],"packages/font_awesome_flutter/lib/fonts/fa-brands-400.ttf":["packages/font_awesome_flutter/lib/fonts/fa-brands-400.ttf"],"packages/font_awesome_flutter/lib/fonts/fa-regular-400.ttf":["packages/font_awesome_flutter/lib/fonts/fa-regular-400.ttf"],"packages/font_awesome_flutter/lib/fonts/fa-solid-900.ttf":["packages/font_awesome_flutter/lib/fonts/fa-solid-900.ttf"]}